README.txt
setup.py
collective/__init__.py
collective.portlet.accuweather.egg-info/PKG-INFO
collective.portlet.accuweather.egg-info/SOURCES.txt
collective.portlet.accuweather.egg-info/dependency_links.txt
collective.portlet.accuweather.egg-info/entry_points.txt
collective.portlet.accuweather.egg-info/namespace_packages.txt
collective.portlet.accuweather.egg-info/not-zip-safe
collective.portlet.accuweather.egg-info/requires.txt
collective.portlet.accuweather.egg-info/top_level.txt
collective/portlet/__init__.py
collective/portlet/accuweather/__init__.py
collective/portlet/accuweather/accuweather.pt
collective/portlet/accuweather/accuweather.py
collective/portlet/accuweather/configure.zcml
collective/portlet/accuweather/icons/01.png
collective/portlet/accuweather/icons/02.png
collective/portlet/accuweather/icons/03.png
collective/portlet/accuweather/icons/04.png
collective/portlet/accuweather/icons/05.png
collective/portlet/accuweather/icons/06.png
collective/portlet/accuweather/icons/07.png
collective/portlet/accuweather/icons/08.png
collective/portlet/accuweather/icons/11.png
collective/portlet/accuweather/icons/12.png
collective/portlet/accuweather/icons/13.png
collective/portlet/accuweather/icons/14.png
collective/portlet/accuweather/icons/15.png
collective/portlet/accuweather/icons/16.png
collective/portlet/accuweather/icons/17.png
collective/portlet/accuweather/icons/18.png
collective/portlet/accuweather/icons/19.png
collective/portlet/accuweather/icons/20.png
collective/portlet/accuweather/icons/21.png
collective/portlet/accuweather/icons/22.png
collective/portlet/accuweather/icons/23.png
collective/portlet/accuweather/icons/24.png
collective/portlet/accuweather/icons/25.png
collective/portlet/accuweather/icons/26.png
collective/portlet/accuweather/icons/29.png
collective/portlet/accuweather/icons/30.png
collective/portlet/accuweather/icons/31.png
collective/portlet/accuweather/icons/32.png
collective/portlet/accuweather/icons/33.png
collective/portlet/accuweather/icons/34.png
collective/portlet/accuweather/icons/35.png
collective/portlet/accuweather/icons/36.png
collective/portlet/accuweather/icons/37.png
collective/portlet/accuweather/icons/38.png
collective/portlet/accuweather/icons/39.png
collective/portlet/accuweather/icons/40.png
collective/portlet/accuweather/icons/41.png
collective/portlet/accuweather/icons/42.png
collective/portlet/accuweather/icons/43.png
