Metadata-Version: 1.0
Name: collective.portlet.accuweather
Version: 1.0b2
Summary: Weather portlet
Home-page: http://pypi.python.org/pypi/collective.portlet.accuweather
Author: Martin Aspeli
Author-email: optilude@gmail.com
License: GPL
Keywords: plone weather portlet
Platform: UNKNOWN
Classifier: Framework :: Plone
Classifier: Programming Language :: Python
Classifier: Topic :: Software Development :: Libraries :: Python Modules
